kiwicalc.py
kiwicalc-0.21.3.dist-info/LICENSE.txt
kiwicalc-0.21.3.dist-info/METADATA
kiwicalc-0.21.3.dist-info/WHEEL
kiwicalc-0.21.3.dist-info/top_level.txt
kiwicalc-0.21.3.dist-info/RECORD
