Metadata-Version: 2.1
Name: kiwicalc
Version: 0.21.3
Summary: Extremely simple interface for mathematics.
Home-page: https://www.kiwicalc.com
Author: Jonathan
Author-email: kiwicalc@gmail.com
License: MIT
Keywords: Math Algebra Calculus Matrix Probability Vector Plot Worksheet PDF
Classifier: License :: OSI Approved :: MIT License
Classifier: Programming Language :: Python :: 3.7
License-File: LICENSE.txt
Requires-Dist: numpy (~=1.21.0)
Requires-Dist: matplotlib (~=3.5.2)
Requires-Dist: reportlab (~=3.6.9)
Requires-Dist: googletrans (~=3.0.0)
Requires-Dist: anytree (~=2.8.0)
Requires-Dist: defusedxml (~=0.7.1)
